pytest_rerunclassfailures/__init__.py
pytest_rerunclassfailures/pytest_rerunclassfailures.py
pytest_rerunclassfailures/requirements.txt
pytest_rerunclassfailures-0.1.1.dist-info/METADATA
pytest_rerunclassfailures-0.1.1.dist-info/WHEEL
pytest_rerunclassfailures-0.1.1.dist-info/entry_points.txt
pytest_rerunclassfailures-0.1.1.dist-info/licenses/LICENSE
pytest_rerunclassfailures-0.1.1.dist-info/RECORD
