Metadata-Version: 2.3
Name: pytest-rerunclassfailures
Version: 0.1.1
Summary: pytest rerun class failures plugin
Project-URL: Homepage, https://github.com/wwakabobik/pytest-rerunclassfailures
Project-URL: Bug Tracker, https://github.com/wwakabobik/pytest-rerunclassfailures/issues
Author-email: Iliya Vereshchagin <i.vereshchagin@gmail.com>
Maintainer-email: Iliya Vereshchagin <i.vereshchagin@gmail.com>
License: MIT License
License-File: LICENSE
Keywords: failures,flacky,pytest,pytest-plugin,pytest-rerunclassfailures,qa,testing
Classifier: Development Status :: 5 - Production/Stable
Classifier: Environment :: Plugins
Classifier: Framework :: Pytest
Classifier: Intended Audience :: Developers
Classifier: Intended Audience :: Information Technology
Classifier: License :: OSI Approved :: MIT License
Classifier: Operating System :: OS Independent
Classifier: Programming Language :: Python :: 3 :: Only
Classifier: Programming Language :: Python :: 3.8
Classifier: Programming Language :: Python :: 3.9
Classifier: Programming Language :: Python :: 3.10
Classifier: Programming Language :: Python :: 3.11
Classifier: Programming Language :: Python :: 3.12
Classifier: Topic :: Software Development :: Libraries :: Python Modules
Classifier: Topic :: Software Development :: Quality Assurance
Classifier: Topic :: Software Development :: Testing
Classifier: Topic :: Utilities
Requires-Python: >=3.8
Requires-Dist: pydantic
Requires-Dist: pytest>=7.2
